setup.py
test/test_tint.py
tint/__init__.py
tint/registry.py
tint.egg-info/PKG-INFO
tint.egg-info/SOURCES.txt
tint.egg-info/dependency_links.txt
tint.egg-info/requires.txt
tint.egg-info/top_level.txt
tint.egg-info/zip-safe
tint/data/en.csv