Metadata-Version: 1.1
Name: tint
Version: 0.4
Summary: Friendly Color Normalization
Home-page: http://github.com/solute/python-tint
Author: Christian Schramm
Author-email: csch@solute.de
License: GPL2
Keywords: color,normalization,fuzzy,perceptual
Platform: UNKNOWN
Classifier: Development Status :: 4 - Beta
Classifier: Intended Audience :: Developers
Classifier: License :: OSI Approved :: GNU General Public License v2 (GPLv2)
Classifier: Topic :: Utilities
Classifier: Programming Language :: Python :: 2
Classifier: Programming Language :: Python :: 2.6
Classifier: Programming Language :: Python :: 2.7
